cjy_wfy/__init__.py
cjy_wfy/main.py
cjy_wfy-0.0.1.dist-info/LICENSE
cjy_wfy-0.0.1.dist-info/METADATA
cjy_wfy-0.0.1.dist-info/WHEEL
cjy_wfy-0.0.1.dist-info/top_level.txt
cjy_wfy-0.0.1.dist-info/RECORD
