Metadata-Version: 2.1
Name: cjy-wfy
Version: 0.0.1
Summary: A small example package
Home-page: UNKNOWN
Author: cjy
Author-email: author@example.com
License: UNKNOWN
Platform: UNKNOWN
Classifier: Programming Language :: Python :: 3
Classifier: License :: OSI Approved :: MIT License
Classifier: Operating System :: OS Independent
Requires-Dist: pygame (==1.9.4)
